adaptmesh/__init__.py
adaptmesh/criterion.py
adaptmesh/initial.py
adaptmesh/mark.py
adaptmesh/process.py
adaptmesh/refine.py
adaptmesh/smooth.py
adaptmesh/solve.py
adaptmesh/meshplex/__init__.py
adaptmesh/meshplex/base.py
adaptmesh/meshplex/exceptions.py
adaptmesh/meshplex/helpers.py
adaptmesh/meshplex/mesh_tri.py
adaptmesh/optimesh/__init__.py
adaptmesh/optimesh/cpt.py
adaptmesh/optimesh/helpers.py
adaptmesh/tri/__init__.py
adaptmesh/tri/delaunay.py
adaptmesh/tri/voronoi.py
adaptmesh-0.3.3.dist-info/LICENSE.md
adaptmesh-0.3.3.dist-info/METADATA
adaptmesh-0.3.3.dist-info/WHEEL
adaptmesh-0.3.3.dist-info/top_level.txt
adaptmesh-0.3.3.dist-info/RECORD
