Metadata-Version: 2.1
Name: adaptmesh
Version: 0.3.3
Summary: Adaptive mesh generation and refinement
Home-page: https://github.com/kinnala/adaptmesh
Author: Tom Gustafsson
License: MIT
Project-URL: Code, https://github.com/kinnala/adaptmesh
Project-URL: Issues, https://github.com/kinnala/adaptmesh/issues
Platform: UNKNOWN
Classifier: Intended Audience :: Science/Research
Classifier: License :: OSI Approved :: MIT License
Classifier: Operating System :: OS Independent
Classifier: Programming Language :: Python
Classifier: Programming Language :: Python :: 3
Classifier: Programming Language :: Python :: 3.6
Classifier: Programming Language :: Python :: 3.7
Classifier: Programming Language :: Python :: 3.8
Classifier: Topic :: Scientific/Engineering
Classifier: Topic :: Utilities
Requires-Python: >=3.6
License-File: LICENSE.md
Requires-Dist: numpy
Requires-Dist: matplotlib
Requires-Dist: scipy
Requires-Dist: scikit-fem (>=3)
Requires-Dist: importlib-metadata ; python_version < "3.8"
